llama_index/selectors/notdiamond/__init__.py
llama_index/selectors/notdiamond/base.py
llama_index_selectors_notdiamond-0.4.0.dist-info/METADATA
llama_index_selectors_notdiamond-0.4.0.dist-info/WHEEL
llama_index_selectors_notdiamond-0.4.0.dist-info/licenses/LICENSE
llama_index_selectors_notdiamond-0.4.0.dist-info/RECORD
