Metadata-Version: 2.4
Name: llama-index-selectors-notdiamond
Version: 0.4.0
Summary: llama-index selectors Not Diamond integration
Author-email: Not Diamond <support@notdiamond.ai>
License-File: LICENSE
Requires-Python: <4,>=3.10
Requires-Dist: litellm
Requires-Dist: llama-index-core<0.15,>=0.10.0
Requires-Dist: notdiamond<0.4,>=0.3.5
